{"type":"FeatureCollection","features":[{"type":"Feature","properties":{"title":"Falafel Inc","message":"cheap food spot"},"geometry":{"coordinates":[-118.44721012454039,34.06295890624429],"type":"Point"},"id":0},{"type":"Feature","properties":{"message":"fav thai food in westwood","title":"Mr. Noodle"},"geometry":{"coordinates":[-118.44686081922532,34.062934568972935],"type":"Point"},"id":1},{"type":"Feature","properties":{"title":"Trader Joes","message":"go to for groceries"},"geometry":{"coordinates":[-118.44394326828521,34.062123794547915],"type":"Point"},"id":2},{"type":"Feature","properties":{"message":"love their handrolls","title":"Kazu Nori"},"geometry":{"coordinates":[-118.44609673665427,34.0600258372192],"type":"Point"}}]}